cognito_assume_role/__init__.py
cognito_assume_role/providers.py
cognito_assume_role-0.0.15.dist-info/LICENSE
cognito_assume_role-0.0.15.dist-info/METADATA
cognito_assume_role-0.0.15.dist-info/WHEEL
cognito_assume_role-0.0.15.dist-info/top_level.txt
cognito_assume_role-0.0.15.dist-info/RECORD
