Metadata-Version: 2.1
Name: cognito-assume-role
Version: 0.0.15
Summary: Assumes an IAM role in boto3 using Cognito credentials
Home-page: https://github.com/QuiNovas/cognito-assume-role
Author: Mathew Moon
Author-email: mmoon@quinovas.com
License: Apache 2.0
Platform: UNKNOWN
Classifier: Development Status :: 3 - Alpha
Classifier: Intended Audience :: Developers
Classifier: License :: OSI Approved :: Apache Software License
Classifier: Programming Language :: Python :: 3.8
Requires-Python: >=3.8
Requires-Dist: boto3
Requires-Dist: botocore
Requires-Dist: warrant
